vanity_address/__init__.py
vanity_address/generate.py
vanity_address/private_key.py
vanity_address/public_key.py
vanity_address/vanity_address.py
vanity_address/lib/__init__.py
vanity_address/lib/encode.py
vanity_address/lib/hash.py
vanity_address-0.1.4.dist-info/LICENSE
vanity_address-0.1.4.dist-info/METADATA
vanity_address-0.1.4.dist-info/WHEEL
vanity_address-0.1.4.dist-info/entry_points.txt
vanity_address-0.1.4.dist-info/top_level.txt
vanity_address-0.1.4.dist-info/RECORD
